{
	"class" : {
		"defaultSpec" : "PeterUhnak 3/4/2016 17:28:40" },
	"instance" : {
		"accessorsCheckbox" : "PeterUhnak 3/4/2016 17:28:40",
		"categoryInput" : "PeterUhnak 3/4/2016 17:28:40",
		"categoryLabel" : "PeterUhnak 3/4/2016 17:28:40",
		"clashPrefixInput" : "PeterUhnak 3/4/2016 17:28:40",
		"clashPrefixLabel" : "PeterUhnak 3/4/2016 17:28:40",
		"createContext" : "PeterUhnak 3/4/2016 17:28:40",
		"generateButton" : "PeterUhnak 3/4/2016 17:28:40",
		"initializeWidgets" : "PeterUhnak 3/4/2016 17:28:40",
		"lazyInitialization" : "PeterUhnak 3/4/2016 17:28:40",
		"methodsCheckbox" : "PeterUhnak 3/4/2016 17:28:40",
		"model:" : "PeterUhnak 3/4/2016 17:28:40",
		"prefixInput" : "PeterUhnak 3/4/2016 17:28:40",
		"prefixLabel" : "PeterUhnak 3/4/2016 17:28:40",
		"runGenerator" : "PeterUhnak 3/4/2016 17:28:40",
		"title" : "PeterUhnak 3/4/2016 17:28:40" } }
