{
	"class" : {
		"defaultSpec" : "PeterUhnak 3/5/2016 00:55:28" },
	"instance" : {
		"autoUpdate" : "PeterUhnak 3/5/2016 00:55:28",
		"buildToolbar:" : "PeterUhnak 3/5/2016 00:55:28",
		"editor" : "PeterUhnak 3/5/2016 00:55:28",
		"initialize" : "PeterUhnak 3/5/2016 00:55:28",
		"initializePresenter" : "PeterUhnak 3/5/2016 00:55:28",
		"initializeWidgets" : "PeterUhnak 3/5/2016 00:55:28",
		"model:" : "PeterUhnak 3/5/2016 00:55:28",
		"openFromFile" : "PeterUhnak 3/5/2016 00:55:28",
		"saveToFile:" : "PeterUhnak 3/5/2016 00:55:28",
		"textUpdated:" : "PeterUhnak 3/5/2016 00:55:28",
		"title" : "PeterUhnak 3/5/2016 00:55:28",
		"toolbar" : "PeterUhnak 3/5/2016 00:55:28",
		"updateFromModel" : "PeterUhnak 3/5/2016 00:55:28",
		"updateModel" : "PeterUhnak 3/5/2016 00:55:28" } }
