{
	"class" : {
		 },
	"instance" : {
		"controllerClass" : "PeterUhnak 3/23/2016 18:07:05",
		"setUp" : "PeterUhnak 3/23/2016 18:07:05",
		"testAddClassController" : "PeterUhnak 3/23/2016 18:07:05",
		"testBuildClass" : "PeterUhnak 3/23/2016 18:07:05",
		"testRemoveClass" : "PeterUhnak 3/23/2016 18:07:05",
		"testRemoveClassWithLinks" : "PeterUhnak 3/23/2016 18:07:05",
		"testRemoveClassWithLinks2" : "PeterUhnak 3/23/2016 18:07:05",
		"testRemoveClassWithProperties" : "PeterUhnak 3/23/2016 18:07:05" } }
