{
	"class" : {
		"current" : "PeterUhnak 3/23/2016 18:07:05" },
	"instance" : {
		"associationIcon" : "PeterUhnak 3/23/2016 18:07:05",
		"associationIconContents" : "PeterUhnak 3/23/2016 18:07:05",
		"classIcon" : "PeterUhnak 3/23/2016 18:07:05",
		"classIconContents" : "PeterUhnak 3/23/2016 18:07:05",
		"diagramIcon" : "PeterUhnak 3/23/2016 18:07:05",
		"diagramIconContents" : "PeterUhnak 3/23/2016 18:07:05",
		"generalizationIcon" : "PeterUhnak 3/23/2016 18:07:05",
		"generalizationIconContents" : "PeterUhnak 3/23/2016 18:07:05",
		"gtInspectorIconsIn:" : "PeterUhnak 3/23/2016 18:07:05",
		"iconSelectors" : "PeterUhnak 3/23/2016 18:07:05",
		"initialize" : "PeterUhnak 3/23/2016 18:07:05",
		"initializeIcons" : "PeterUhnak 3/23/2016 18:07:05" } }
