{
	"class" : {
		 },
	"instance" : {
		"addAssociationEndFigures:at:" : "PeterUhnak 1/11/2016 22:57:31",
		"addAssociationFigures" : "PeterUhnak 1/11/2016 22:57:31",
		"attachFigure" : "PeterUhnak 1/11/2016 22:57:31",
		"buildEditorForm:" : "PeterUhnak 1/11/2016 22:57:31",
		"buildEditorForm:for:" : "PeterUhnak 1/11/2016 22:57:31",
		"createEdgeFrom:to:" : "PeterUhnak 1/11/2016 22:57:31",
		"createModel" : "PeterUhnak 1/11/2016 22:57:31",
		"edgeBuilder" : "PeterUhnak 1/11/2016 22:57:31",
		"modelClass" : "PeterUhnak 1/11/2016 22:57:31",
		"multiplicityRangeFor:" : "PeterUhnak 1/11/2016 22:57:31",
		"refreshEndFigure:decoratorSelector:" : "PeterUhnak 1/11/2016 22:57:31",
		"refreshFigure" : "PeterUhnak 1/11/2016 22:57:31" } }
