{
	"class" : {
		 },
	"instance" : {
		"center" : "PeterUhnak 10/12/2015 15:44:20",
		"changed:" : "PeterUhnak 10/12/2015 15:44:20",
		"createRtElement" : "PeterUhnak 10/12/2015 15:44:20",
		"encompassingRectangle" : "PeterUhnak 10/12/2015 15:44:20",
		"extent" : "PeterUhnak 10/12/2015 15:44:20",
		"extent:" : "PeterUhnak 10/12/2015 15:44:20",
		"height" : "PeterUhnak 10/12/2015 15:44:20",
		"height:" : "PeterUhnak 10/12/2015 15:44:20",
		"rtElement" : "PeterUhnak 10/12/2015 15:44:20",
		"translateBy:" : "PeterUhnak 10/12/2015 15:44:20",
		"translateTo:" : "PeterUhnak 10/12/2015 15:44:20",
		"update" : "PeterUhnak 10/12/2015 15:44:20",
		"update:" : "PeterUhnak 10/12/2015 15:44:20",
		"view" : "PeterUhnak 10/12/2015 15:44:20",
		"width" : "PeterUhnak 10/12/2015 15:44:20",
		"width:" : "PeterUhnak 10/12/2015 15:44:20" } }
